{
  "bookId": "book3",
  "sectionId": "section1",
  "sectionTitle": "School Starts | 開學了",
  "items": [
    {
      "id": 1,
      "chinese": "安德思",
      "pinyin": "Ān Désī",
      "english": "a man from Honduras",
      "sentenceChinese": "安德思是從宏都拉斯來的學生。",
      "sentencePinyin": "Ān Désī shì cóng Hóngdūlāsī lái de xuéshēng.",
      "sentenceEnglish": "Andres is a student from Honduras.",
      "vietnamese": "An Đức Tư (một nam sinh đến từ Honduras)",
      "sentenceVietnamese": "An Đức Tư là một du học sinh đến từ Honduras."
    },
    {
      "id": 2,
      "chinese": "羅珊蒂和何雅婷",
      "pinyin": "Luó Shāndì hé Hé Yǎtíng",
      "english": "Rosandy and He Yating",
      "sentenceChinese": "羅珊蒂和何雅婷都是這一班的新生。",
      "sentencePinyin": "Luó Shāndì hé Hé Yǎtíng dōu shì zhè yì bān de xīnshēng.",
      "sentenceEnglish": "Rosandy and He Yating are both new students in this class.",
      "vietnamese": "La San Đế và Hà Nhã Đình",
      "sentenceVietnamese": "La San Đế và Hà Nhã Đình đều là tân sinh viên của lớp này."
    },
    {
      "id": 3,
      "chinese": "開學",
      "pinyin": "kāixué",
      "english": "school starts; to begin a new semester",
      "sentenceChinese": "下星期就要開學了。",
      "sentencePinyin": "Xià xīngqī jiù yào kāixué le.",
      "sentenceEnglish": "School starts next week.",
      "vietnamese": "khai giảng; bắt đầu học kỳ mới",
      "sentenceVietnamese": "Tuần sau là bắt đầu khai giảng rồi."
    },
    {
      "id": 4,
      "chinese": "班",
      "pinyin": "bān",
      "english": "class",
      "sentenceChinese": "我們班有二十個學生。",
      "sentencePinyin": "Wǒmen bān yǒu èrshí ge xuéshēng.",
      "sentenceEnglish": "There are twenty students in our class.",
      "vietnamese": "lớp",
      "sentenceVietnamese": "Lớp chúng tôi có 20 học sinh."
    },
    {
      "id": 5,
      "chinese": "新生",
      "pinyin": "xīnshēng",
      "english": "new student; freshman",
      "sentenceChinese": "今天有很多新生來報到。",
      "sentencePinyin": "Jīntiān yǒu hěnduō xīnshēng lái bàodào.",
      "sentenceEnglish": "Many new students came to register today.",
      "vietnamese": "tân sinh viên",
      "sentenceVietnamese": "Hôm nay có rất nhiều tân sinh viên đến làm thủ tục nhập học."
    },
    {
      "id": 6,
      "chinese": "嚴",
      "pinyin": "yán",
      "english": "strict",
      "sentenceChinese": "這位老師很嚴，但是很關心學生。",
      "sentencePinyin": "Zhè wèi lǎoshī hěn yán, dànshì hěn guānxīn xuéshēng.",
      "sentenceEnglish": "This teacher is strict, but cares a lot about the students.",
      "vietnamese": "nghiêm khắc",
      "sentenceVietnamese": "Giáo viên này rất nghiêm khắc, nhưng rất quan tâm học sinh."
    },
    {
      "id": 7,
      "chinese": "口試",
      "pinyin": "kǒushì",
      "english": "oral test",
      "sentenceChinese": "明天上午有口試。",
      "sentencePinyin": "Míngtiān shàngwǔ yǒu kǒushì.",
      "sentenceEnglish": "There is an oral test tomorrow morning.",
      "vietnamese": "kiểm tra vấn đáp",
      "sentenceVietnamese": "Sáng mai có bài kiểm tra vấn đáp."
    },
    {
      "id": 8,
      "chinese": "筆試",
      "pinyin": "bǐshì",
      "english": "written test",
      "sentenceChinese": "這次筆試比上次難。",
      "sentencePinyin": "Zhè cì bǐshì bǐ shàng cì nán.",
      "sentenceEnglish": "This written test is harder than the last one.",
      "vietnamese": "kiểm tra viết",
      "sentenceVietnamese": "Bài kiểm tra viết lần này khó hơn lần trước."
    },
    {
      "id": 9,
      "chinese": "以外",
      "pinyin": "yǐwài",
      "english": "besides; except for",
      "sentenceChinese": "除了中文以外，他也會說日文。",
      "sentencePinyin": "Chúle Zhōngwén yǐwài, tā yě huì shuō Rìwén.",
      "sentenceEnglish": "Besides Chinese, he can also speak Japanese.",
      "vietnamese": "ngoài ... ra",
      "sentenceVietnamese": "Ngoài tiếng Trung ra, anh ấy còn biết nói tiếng Nhật."
    },
    {
      "id": 10,
      "chinese": "口頭",
      "pinyin": "kǒutóu",
      "english": "oral; spoken",
      "sentenceChinese": "老師先做口頭說明，再發資料。",
      "sentencePinyin": "Lǎoshī xiān zuò kǒutóu shuōmíng, zài fā zīliào.",
      "sentenceEnglish": "The teacher first gave an oral explanation, then handed out the materials.",
      "vietnamese": "bằng miệng; bằng lời",
      "sentenceVietnamese": "Giáo viên giải thích bằng lời trước rồi mới phát tài liệu."
    },
    {
      "id": 11,
      "chinese": "報告",
      "pinyin": "bàogào",
      "english": "report; presentation",
      "sentenceChinese": "我下星期要做中文報告。",
      "sentencePinyin": "Wǒ xià xīngqī yào zuò Zhōngwén bàogào.",
      "sentenceEnglish": "I have to give a Chinese presentation next week.",
      "vietnamese": "báo cáo; thuyết trình",
      "sentenceVietnamese": "Tuần sau tôi phải thuyết trình bằng tiếng Trung."
    },
    {
      "id": 12,
      "chinese": "壓力",
      "pinyin": "yālì",
      "english": "pressure; stress",
      "sentenceChinese": "最近功課很多，我的壓力很大。",
      "sentencePinyin": "Zuìjìn gōngkè hěnduō, wǒ de yālì hěn dà.",
      "sentenceEnglish": "I have a lot of homework lately, so I am under a lot of pressure.",
      "vietnamese": "áp lực",
      "sentenceVietnamese": "Dạo này bài tập nhiều nên tôi cảm thấy rất áp lực."
    },
    {
      "id": 13,
      "chinese": "說明",
      "pinyin": "shuōmíng",
      "english": "to explain; explanation",
      "sentenceChinese": "老師把考試規則說明得很清楚。",
      "sentencePinyin": "Lǎoshī bǎ kǎoshì guīzé shuōmíng de hěn qīngchǔ.",
      "sentenceEnglish": "The teacher explained the test rules very clearly.",
      "vietnamese": "giải thích; phần giải thích",
      "sentenceVietnamese": "Giáo viên giải thích quy định của kỳ thi rất rõ ràng."
    },
    {
      "id": 14,
      "chinese": "清楚",
      "pinyin": "qīngchǔ",
      "english": "clear; clearly",
      "sentenceChinese": "請你說清楚一點。",
      "sentencePinyin": "Qǐng nǐ shuō qīngchǔ yìdiǎn.",
      "sentenceEnglish": "Please explain it a little more clearly.",
      "vietnamese": "rõ ràng",
      "sentenceVietnamese": "Bạn hãy nói rõ hơn một chút."
    },
    {
      "id": 15,
      "chinese": "位子",
      "pinyin": "wèizi",
      "english": "seat; place",
      "sentenceChinese": "教室裡還有一個空位子。",
      "sentencePinyin": "Jiàoshì lǐ hái yǒu yí ge kōng wèizi.",
      "sentenceEnglish": "There is still an empty seat in the classroom.",
      "vietnamese": "chỗ ngồi; vị trí",
      "sentenceVietnamese": "Trong lớp vẫn còn một chỗ ngồi trống."
    },
    {
      "id": 16,
      "chinese": "旁聽",
      "pinyin": "pángtīng",
      "english": "to audit a class",
      "sentenceChinese": "他想旁聽這門課。",
      "sentencePinyin": "Tā xiǎng pángtīng zhè mén kè.",
      "sentenceEnglish": "He wants to audit this course.",
      "vietnamese": "học dự thính",
      "sentenceVietnamese": "Anh ấy muốn vào dự thính môn học này."
    },
    {
      "id": 17,
      "chinese": "分",
      "pinyin": "fēn",
      "english": "points; score",
      "sentenceChinese": "他這次考了九十分。",
      "sentencePinyin": "Tā zhè cì kǎo le jiǔshí fēn.",
      "sentenceEnglish": "He got ninety points on this test.",
      "vietnamese": "điểm",
      "sentenceVietnamese": "Lần này anh ấy thi được 90 điểm."
    },
    {
      "id": 18,
      "chinese": "羨慕",
      "pinyin": "xiànmù",
      "english": "to envy; to admire",
      "sentenceChinese": "我很羨慕他的口才。",
      "sentencePinyin": "Wǒ hěn xiànmù tā de kǒucái.",
      "sentenceEnglish": "I really admire his speaking skills.",
      "vietnamese": "ngưỡng mộ; ghen tị",
      "sentenceVietnamese": "Tôi rất ngưỡng mộ khả năng ăn nói của anh ấy."
    },
    {
      "id": 19,
      "chinese": "休學",
      "pinyin": "xiūxué",
      "english": "to suspend one’s studies",
      "sentenceChinese": "他因為身體不好，決定先休學一年。",
      "sentencePinyin": "Tā yīnwèi shēntǐ bù hǎo, juédìng xiān xiūxué yì nián.",
      "sentenceEnglish": "Because of poor health, he decided to suspend his studies for a year.",
      "vietnamese": "bảo lưu; tạm ngừng việc học",
      "sentenceVietnamese": "Vì sức khỏe không tốt nên anh ấy quyết định bảo lưu một năm."
    },
    {
      "id": 20,
      "chinese": "用功",
      "pinyin": "yònggōng",
      "english": "diligent; hardworking in study",
      "sentenceChinese": "她平常很用功，所以成績很好。",
      "sentencePinyin": "Tā píngcháng hěn yònggōng, suǒyǐ chéngjī hěn hǎo.",
      "sentenceEnglish": "She studies hard, so her grades are very good.",
      "vietnamese": "chăm chỉ học hành",
      "sentenceVietnamese": "Bình thường cô ấy rất chăm học nên thành tích rất tốt."
    },
    {
      "id": 21,
      "chinese": "行",
      "pinyin": "xíng",
      "english": "okay; possible",
      "sentenceChinese": "這樣安排行不行？",
      "sentencePinyin": "Zhèyàng ānpái xíng bu xíng?",
      "sentenceEnglish": "Is this arrangement okay?",
      "vietnamese": "được; ổn",
      "sentenceVietnamese": "Sắp xếp như vậy có được không?"
    },
    {
      "id": 22,
      "chinese": "轉",
      "pinyin": "zhuǎn",
      "english": "to transfer; to switch",
      "sentenceChinese": "他想下學期轉系。",
      "sentencePinyin": "Tā xiǎng xià xuéqí zhuǎn xì.",
      "sentenceEnglish": "He wants to transfer to another department next semester.",
      "vietnamese": "chuyển; đổi",
      "sentenceVietnamese": "Anh ấy muốn chuyển khoa vào học kỳ sau."
    },
    {
      "id": 23,
      "chinese": "原來",
      "pinyin": "yuánlái",
      "english": "so it turns out; originally",
      "sentenceChinese": "原來你也是這個系的學生。",
      "sentencePinyin": "Yuánlái nǐ yě shì zhège xì de xuéshēng.",
      "sentenceEnglish": "So you are also a student in this department.",
      "vietnamese": "ra là; hóa ra",
      "sentenceVietnamese": "Hóa ra bạn cũng là sinh viên của khoa này."
    },
    {
      "id": 24,
      "chinese": "會計",
      "pinyin": "kuàijì",
      "english": "accounting",
      "sentenceChinese": "她大學念會計。",
      "sentencePinyin": "Tā dàxué niàn kuàijì.",
      "sentenceEnglish": "She majored in accounting in college.",
      "vietnamese": "kế toán",
      "sentenceVietnamese": "Cô ấy học ngành kế toán ở đại học."
    },
    {
      "id": 25,
      "chinese": "熱門",
      "pinyin": "rèmén",
      "english": "popular; in demand",
      "sentenceChinese": "這個科系現在很熱門。",
      "sentencePinyin": "Zhège kēxì xiànzài hěn rèmén.",
      "sentenceEnglish": "This department is very popular right now.",
      "vietnamese": "hot; được nhiều người chọn",
      "sentenceVietnamese": "Ngành này hiện nay rất được nhiều người quan tâm."
    },
    {
      "id": 26,
      "chinese": "熬夜",
      "pinyin": "áoyè",
      "english": "to stay up late",
      "sentenceChinese": "昨天晚上我熬夜寫報告。",
      "sentencePinyin": "Zuótiān wǎnshàng wǒ áoyè xiě bàogào.",
      "sentenceEnglish": "I stayed up late last night writing my report.",
      "vietnamese": "thức khuya",
      "sentenceVietnamese": "Tối qua tôi thức khuya để viết báo cáo."
    },
    {
      "id": 27,
      "chinese": "當",
      "pinyin": "dàng",
      "english": "to fail a course",
      "sentenceChinese": "他上學期當了兩門課。",
      "sentencePinyin": "Tā shàng xuéqí dàng le liǎng mén kè.",
      "sentenceEnglish": "He failed two courses last semester.",
      "vietnamese": "rớt môn",
      "sentenceVietnamese": "Học kỳ trước anh ấy bị rớt hai môn."
    },
    {
      "id": 28,
      "chinese": "恐怕",
      "pinyin": "kǒngpà",
      "english": "I’m afraid; probably",
      "sentenceChinese": "你來晚了，恐怕沒有位子了。",
      "sentencePinyin": "Nǐ lái wǎn le, kǒngpà méiyǒu wèizi le.",
      "sentenceEnglish": "You are late. I am afraid there are no seats left.",
      "vietnamese": "e rằng; có lẽ",
      "sentenceVietnamese": "Bạn đến muộn rồi, e là không còn chỗ nữa."
    },
    {
      "id": 29,
      "chinese": "口才",
      "pinyin": "kǒucái",
      "english": "eloquence; speaking skills",
      "sentenceChinese": "他的口才很好，很適合做業務。",
      "sentencePinyin": "Tā de kǒucái hěn hǎo, hěn shìhé zuò yèwù.",
      "sentenceEnglish": "He speaks very well and is well suited to sales work.",
      "vietnamese": "khả năng ăn nói",
      "sentenceVietnamese": "Anh ấy ăn nói rất khéo, rất hợp làm công việc kinh doanh."
    },
    {
      "id": 30,
      "chinese": "事",
      "pinyin": "shì",
      "english": "matter; thing",
      "sentenceChinese": "這件事你先別告訴他。",
      "sentencePinyin": "Zhè jiàn shì nǐ xiān bié gàosu tā.",
      "sentenceEnglish": "Don’t tell him about this matter yet.",
      "vietnamese": "việc; chuyện",
      "sentenceVietnamese": "Chuyện này trước mắt bạn đừng nói với anh ấy."
    },
    {
      "id": 31,
      "chinese": "遲到",
      "pinyin": "chídào",
      "english": "to be late",
      "sentenceChinese": "他今天又遲到了。",
      "sentencePinyin": "Tā jīntiān yòu chídào le.",
      "sentenceEnglish": "He was late again today.",
      "vietnamese": "đi muộn",
      "sentenceVietnamese": "Hôm nay anh ấy lại đến muộn rồi."
    },
    {
      "id": 32,
      "chinese": "差一點",
      "pinyin": "chà yìdiǎn",
      "english": "almost; nearly",
      "sentenceChinese": "我差一點忘了今天有口試。",
      "sentencePinyin": "Wǒ chà yìdiǎn wàng le jīntiān yǒu kǒushì.",
      "sentenceEnglish": "I almost forgot that there is an oral test today.",
      "vietnamese": "suýt nữa",
      "sentenceVietnamese": "Tôi suýt nữa quên mất hôm nay có kiểm tra vấn đáp."
    },
    {
      "id": 33,
      "chinese": "這樣下去",
      "pinyin": "zhèyàng xiàqù",
      "english": "if this continues; going on like this",
      "sentenceChinese": "你再不休息，這樣下去身體會吃不消。",
      "sentencePinyin": "Nǐ zài bù xiūxí, zhèyàng xiàqù shēntǐ huì chī bù xiāo.",
      "sentenceEnglish": "If you keep going like this without resting, your body will not be able to take it.",
      "vietnamese": "nếu cứ thế này",
      "sentenceVietnamese": "Nếu bạn không nghỉ ngơi mà cứ thế này thì cơ thể sẽ không chịu nổi."
    },
    {
      "id": 34,
      "chinese": "沒辦法",
      "pinyin": "méi bànfǎ",
      "english": "there’s no way; cannot help it",
      "sentenceChinese": "今天下大雨，我沒辦法出門。",
      "sentencePinyin": "Jīntiān xià dàyǔ, wǒ méi bànfǎ chūmén.",
      "sentenceEnglish": "It is raining heavily today, so I cannot go out.",
      "vietnamese": "không có cách nào; đành chịu",
      "sentenceVietnamese": "Hôm nay mưa to quá nên tôi không có cách nào ra ngoài được."
    },
    {
      "id": 35,
      "chinese": "獨生女",
      "pinyin": "dúshēngnǚ",
      "english": "only daughter",
      "sentenceChinese": "她是家裡的獨生女。",
      "sentencePinyin": "Tā shì jiālǐ de dúshēngnǚ.",
      "sentenceEnglish": "She is the only daughter in her family.",
      "vietnamese": "con gái duy nhất",
      "sentenceVietnamese": "Cô ấy là con gái duy nhất trong nhà."
    },
    {
      "id": 36,
      "chinese": "私立",
      "pinyin": "sīlì",
      "english": "private",
      "sentenceChinese": "他念的是一所私立大學。",
      "sentencePinyin": "Tā niàn de shì yì suǒ sīlì dàxué.",
      "sentenceEnglish": "He studies at a private university.",
      "vietnamese": "tư lập",
      "sentenceVietnamese": "Anh ấy đang học ở một trường đại học tư lập."
    },
    {
      "id": 37,
      "chinese": "理想",
      "pinyin": "lǐxiǎng",
      "english": "ideal; dream",
      "sentenceChinese": "當老師是她的理想。",
      "sentencePinyin": "Dāng lǎoshī shì tā de lǐxiǎng.",
      "sentenceEnglish": "Becoming a teacher is her dream.",
      "vietnamese": "lý tưởng; ước mơ",
      "sentenceVietnamese": "Làm giáo viên là ước mơ của cô ấy."
    },
    {
      "id": 38,
      "chinese": "合",
      "pinyin": "hé",
      "english": "to fit; to suit",
      "sentenceChinese": "這雙鞋很合我的腳。",
      "sentencePinyin": "Zhè shuāng xié hěn hé wǒ de jiǎo.",
      "sentenceEnglish": "These shoes fit me well.",
      "vietnamese": "hợp; vừa",
      "sentenceVietnamese": "Đôi giày này rất vừa chân tôi."
    },
    {
      "id": 39,
      "chinese": "痛苦",
      "pinyin": "tòngkǔ",
      "english": "painful; miserable",
      "sentenceChinese": "準備考試的時候最痛苦。",
      "sentencePinyin": "Zhǔnbèi kǎoshì de shíhòu zuì tòngkǔ.",
      "sentenceEnglish": "The hardest part is preparing for the exam.",
      "vietnamese": "đau khổ; khổ sở",
      "sentenceVietnamese": "Lúc chuẩn bị cho kỳ thi là lúc khổ sở nhất."
    },
    {
      "id": 40,
      "chinese": "科系",
      "pinyin": "kēxì",
      "english": "department; academic program",
      "sentenceChinese": "你想申請哪一個科系？",
      "sentencePinyin": "Nǐ xiǎng shēnqǐng nǎ yí ge kēxì?",
      "sentenceEnglish": "Which department do you want to apply to?",
      "vietnamese": "khoa; ngành học",
      "sentenceVietnamese": "Bạn muốn đăng ký vào khoa nào?"
    },
    {
      "id": 41,
      "chinese": "放棄",
      "pinyin": "fàngqì",
      "english": "to give up",
      "sentenceChinese": "這門課雖然難，我也不想放棄。",
      "sentencePinyin": "Zhè mén kè suīrán nán, wǒ yě bù xiǎng fàngqì.",
      "sentenceEnglish": "Although this course is difficult, I still don’t want to give up.",
      "vietnamese": "bỏ cuộc; từ bỏ",
      "sentenceVietnamese": "Môn học này tuy khó nhưng tôi vẫn không muốn bỏ cuộc."
    },
    {
      "id": 42,
      "chinese": "不管",
      "pinyin": "bùguǎn",
      "english": "no matter; regardless of",
      "sentenceChinese": "不管多忙，他都會準時上課。",
      "sentencePinyin": "Bùguǎn duō máng, tā dōu huì zhǔnshí shàngkè.",
      "sentenceEnglish": "No matter how busy he is, he always comes to class on time.",
      "vietnamese": "bất kể",
      "sentenceVietnamese": "Bất kể bận đến đâu, anh ấy cũng đi học đúng giờ."
    },
    {
      "id": 43,
      "chinese": "反對",
      "pinyin": "fǎnduì",
      "english": "to oppose",
      "sentenceChinese": "我父母不反對我出國留學。",
      "sentencePinyin": "Wǒ fùmǔ bù fǎnduì wǒ chūguó liúxué.",
      "sentenceEnglish": "My parents do not oppose my studying abroad.",
      "vietnamese": "phản đối",
      "sentenceVietnamese": "Bố mẹ tôi không phản đối việc tôi đi du học."
    },
    {
      "id": 44,
      "chinese": "個性",
      "pinyin": "gèxìng",
      "english": "personality",
      "sentenceChinese": "她的個性很開朗。",
      "sentencePinyin": "Tā de gèxìng hěn kāilǎng.",
      "sentenceEnglish": "She has a cheerful personality.",
      "vietnamese": "tính cách",
      "sentenceVietnamese": "Tính cách của cô ấy rất vui vẻ."
    },
    {
      "id": 45,
      "chinese": "活潑",
      "pinyin": "huópō",
      "english": "lively; cheerful",
      "sentenceChinese": "那個小女孩很活潑。",
      "sentencePinyin": "Nàge xiǎo nǚhái hěn huópō.",
      "sentenceEnglish": "That little girl is very lively.",
      "vietnamese": "hoạt bát",
      "sentenceVietnamese": "Bé gái đó rất hoạt bát."
    },
    {
      "id": 46,
      "chinese": "外語",
      "pinyin": "wàiyǔ",
      "english": "foreign language",
      "sentenceChinese": "我最喜歡學外語。",
      "sentencePinyin": "Wǒ zuì xǐhuān xué wàiyǔ.",
      "sentenceEnglish": "I like studying foreign languages the most.",
      "vietnamese": "ngoại ngữ",
      "sentenceVietnamese": "Tôi thích học ngoại ngữ nhất."
    },
    {
      "id": 47,
      "chinese": "擔心",
      "pinyin": "dānxīn",
      "english": "to worry",
      "sentenceChinese": "明天有筆試，我有一點擔心。",
      "sentencePinyin": "Míngtiān yǒu bǐshì, wǒ yǒu yìdiǎn dānxīn.",
      "sentenceEnglish": "There is a written test tomorrow, and I am a little worried.",
      "vietnamese": "lo lắng",
      "sentenceVietnamese": "Ngày mai có bài kiểm tra viết nên tôi hơi lo."
    },
    {
      "id": 48,
      "chinese": "填表",
      "pinyin": "tiánbiǎo",
      "english": "to fill out a form",
      "sentenceChinese": "先填表，再去辦手續。",
      "sentencePinyin": "Xiān tiánbiǎo, zài qù bàn shǒuxù.",
      "sentenceEnglish": "Fill out the form first, then go complete the procedures.",
      "vietnamese": "điền biểu mẫu",
      "sentenceVietnamese": "Hãy điền mẫu đơn trước rồi mới đi làm thủ tục."
    },
    {
      "id": 49,
      "chinese": "辦理",
      "pinyin": "bànlǐ",
      "english": "to handle; to process",
      "sentenceChinese": "你可以去教務處辦理休學。",
      "sentencePinyin": "Nǐ kěyǐ qù jiàowùchù bànlǐ xiūxué.",
      "sentenceEnglish": "You can go to the academic affairs office to apply for suspension of studies.",
      "vietnamese": "làm; xử lý thủ tục",
      "sentenceVietnamese": "Bạn có thể đến phòng giáo vụ để làm thủ tục bảo lưu."
    },
    {
      "id": 50,
      "chinese": "手續",
      "pinyin": "shǒuxù",
      "english": "procedures; formalities",
      "sentenceChinese": "申請簽證的手續很麻煩。",
      "sentencePinyin": "Shēnqǐng qiānzhèng de shǒuxù hěn máfan.",
      "sentenceEnglish": "The procedures for applying for a visa are complicated.",
      "vietnamese": "thủ tục",
      "sentenceVietnamese": "Thủ tục xin visa rất phiền phức."
    },
    {
      "id": 51,
      "chinese": "申請",
      "pinyin": "shēnqǐng",
      "english": "to apply for",
      "sentenceChinese": "她想申請獎學金。",
      "sentencePinyin": "Tā xiǎng shēnqǐng jiǎngxuéjīn.",
      "sentenceEnglish": "She wants to apply for a scholarship.",
      "vietnamese": "xin; đăng ký",
      "sentenceVietnamese": "Cô ấy muốn xin học bổng."
    },
    {
      "id": 52,
      "chinese": "成績單",
      "pinyin": "chéngjìdān",
      "english": "transcript; report card",
      "sentenceChinese": "請把成績單交給老師。",
      "sentencePinyin": "Qǐng bǎ chéngjìdān jiāo gěi lǎoshī.",
      "sentenceEnglish": "Please hand your transcript to the teacher.",
      "vietnamese": "bảng điểm",
      "sentenceVietnamese": "Hãy nộp bảng điểm cho giáo viên."
    },
    {
      "id": 53,
      "chinese": "考上",
      "pinyin": "kǎoshàng",
      "english": "to pass an entrance exam and get into",
      "sentenceChinese": "他終於考上理想的大學了。",
      "sentencePinyin": "Tā zhōngyú kǎoshàng lǐxiǎng de dàxué le.",
      "sentenceEnglish": "He finally got into the university he had hoped for.",
      "vietnamese": "thi đậu",
      "sentenceVietnamese": "Cuối cùng anh ấy cũng thi đậu vào trường đại học mơ ước."
    },
    {
      "id": 54,
      "chinese": "推薦信",
      "pinyin": "tuījiànxìn",
      "english": "letter of recommendation",
      "sentenceChinese": "申請研究所需要兩封推薦信。",
      "sentencePinyin": "Shēnqǐng yánjiùsuǒ xūyào liǎng fēng tuījiànxìn.",
      "sentenceEnglish": "Applying to graduate school requires two letters of recommendation.",
      "vietnamese": "thư giới thiệu",
      "sentenceVietnamese": "Nộp hồ sơ cao học cần hai lá thư giới thiệu."
    },
    {
      "id": 55,
      "chinese": "羅珊蒂",
      "pinyin": "Luó Shāndì",
      "english": "a woman from Indonesia",
      "sentenceChinese": "羅珊蒂是從印尼來的學生。",
      "sentencePinyin": "Luó Shāndì shì cóng Yìnní lái de xuéshēng.",
      "sentenceEnglish": "Rosandy is a student from Indonesia.",
      "vietnamese": "La San Đế (một nữ sinh đến từ Indonesia)",
      "sentenceVietnamese": "La San Đế là một nữ sinh đến từ Indonesia."
    },
    {
      "id": 56,
      "chinese": "何雅婷",
      "pinyin": "Hé Yǎtíng",
      "english": "a woman from Taiwan",
      "sentenceChinese": "何雅婷是台灣人。",
      "sentencePinyin": "Hé Yǎtíng shì Táiwān rén.",
      "sentenceEnglish": "He Yating is from Taiwan.",
      "vietnamese": "Hà Nhã Đình (một nữ sinh đến từ Đài Loan)",
      "sentenceVietnamese": "Hà Nhã Đình là người Đài Loan."
    }
  ],
  "theme": "School Starts"
}
