{
  "bookId": "book3",
  "sectionId": "section12",
  "sectionTitle": "I'm Going to Cast My Vote | 我要去投票",
  "items": [
    {
      "id": 1,
      "chinese": "投票",
      "pinyin": "tóupiào",
      "en": "to vote",
      "vi": "bỏ phiếu",
      "sinoVietnamese": "",
      "samples": [
        {
          "type": "sv",
          "meaning": "vote; cast a vote",
          "sentence": "他投票支持這個提案。",
          "pinyin": "tā tóupiào zhīchí zhège tí'àn.",
          "en": "He voted in support of this proposal.",
          "vi": "Anh ấy bỏ phiếu ủng hộ đề án này."
        },
        {
          "type": "sv",
          "meaning": "vote; cast a vote",
          "sentence": "我們今天要去投票。",
          "pinyin": "wǒmen jīntiān yào qù tóupiào.",
          "en": "We are going to vote today.",
          "vi": "Hôm nay chúng tôi phải đi bầu cử."
        }
      ]
    },
    {
      "id": 2,
      "chinese": "抱歉",
      "pinyin": "bàoqiàn",
      "en": "sorry; apologetic",
      "vi": "xin lỗi",
      "sinoVietnamese": "",
      "samples": [
        {
          "type": "Adjective",
          "meaning": "sorry; apologetic; regretful",
          "sentence": "她真心地感到抱歉。",
          "pinyin": "tā zhēnxīn de gǎndào bàoqiàn",
          "en": "She was truly sorry.",
          "vi": ""
        },
        {
          "type": "Adjective",
          "meaning": "sorry; apologetic; regretful",
          "sentence": "他一臉抱歉地看著我。",
          "pinyin": "tā yī liǎn bàoqiàn de kànzhe wǒ.",
          "en": "He looked at me with an apologetic expression.",
          "vi": "Anh ấy mặt đầy áy náy nhìn tôi."
        }
      ]
    },
    {
      "id": 3,
      "chinese": "表妹",
      "pinyin": "biǎomèi",
      "en": "younger female cousin",
      "vi": "em họ (nữ)",
      "sinoVietnamese": "",
      "samples": [
        {
          "type": "Noun",
          "meaning": "younger female cousin; cousin on the female line",
          "sentence": "錶妹給我買了一份禮物。",
          "pinyin": "biǎomèi gěi wǒ mǎile yī fèn lǐwù.",
          "en": "My younger female cousin bought me a gift.",
          "vi": "Em họ đã mua cho tôi một món quà."
        },
        {
          "type": "Noun",
          "meaning": "younger female cousin; cousin on the female line",
          "sentence": "我的錶妹很喜歡彈鋼琴。",
          "pinyin": "wǒ de biǎomèi hěn xǐhuan tán gāngqín.",
          "en": "My younger female cousin loves playing the piano.",
          "vi": ""
        }
      ]
    },
    {
      "id": 4,
      "chinese": "反核",
      "pinyin": "fǎn hé",
      "en": "anti-nuclear",
      "vi": "phản hạt nhân",
      "sinoVietnamese": "",
      "samples": [
        {
          "type": "Verb",
          "meaning": "anti-nuclear (e.g. protest)",
          "sentence": "政府麵對反核/覈示威遊行。",
          "pinyin": "Zhèngfǔ miànduì fǎnhé shìwēi yóuxíng.",
          "en": "The government faces anti-nuclear protest marches.",
          "vi": ""
        }
      ]
    },
    {
      "id": 5,
      "chinese": "遊行",
      "pinyin": "yóuxíng",
      "en": "demonstration; march",
      "vi": "diễu hành; tuần hành",
      "sinoVietnamese": "",
      "samples": [
        {
          "type": "Verb",
          "meaning": "parade; march; demonstration",
          "sentence": "人們在舉行慶祝遊行活動。",
          "pinyin": "rénmen zài jǔxíng qìngzhù yóuxíng huódòng.",
          "en": "People are holding a celebration parade.",
          "vi": ""
        },
        {
          "type": "Verb",
          "meaning": "parade; march; demonstration",
          "sentence": "上萬人在廣場舉行了遊行。",
          "pinyin": "shàng wàn rén zài guǎngchǎng jǔxíngle yóuxíng.",
          "en": "Tens of thousands of people marched in the squar.",
          "vi": ""
        }
      ]
    },
    {
      "id": 6,
      "chinese": "政治",
      "pinyin": "zhèngzhì",
      "en": "politics",
      "vi": "chính trị",
      "sinoVietnamese": "",
      "samples": [
        {
          "type": "Noun",
          "meaning": "politics; political affairs",
          "sentence": "他對政治很感興趣。",
          "pinyin": "tā duì zhèngzhì hěn gǎn xìngqù.",
          "en": "He is very interested in politics.",
          "vi": "Anh ấy rất quan tâm đến chính trị."
        },
        {
          "type": "Noun",
          "meaning": "politics; political affairs",
          "sentence": "學校有政治活動。",
          "pinyin": "xuéxiào yǒu zhèngzhì huódòng.",
          "en": "There are political activities in the school.",
          "vi": "Trường có các hoạt động chính trị."
        }
      ]
    },
    {
      "id": 7,
      "chinese": "熱衷",
      "pinyin": "rèzhōng",
      "en": "enthusiastic about; passionate about",
      "vi": "say mê; nhiệt tình với",
      "sinoVietnamese": "",
      "samples": [
        {
          "type": "Verb",
          "meaning": "be fond of; be keen on",
          "sentence": "我對健身很熱衷。",
          "pinyin": "wǒ duì jiànshēn hěn rèzhōng.",
          "en": "I am keen on fitness.",
          "vi": ""
        },
        {
          "type": "Verb",
          "meaning": "be fond of; be keen on",
          "sentence": "她對創作非常熱衷。",
          "pinyin": "tā duì chuàngzuò fēicháng rèzhōng.",
          "en": "She is very fond of creation.",
          "vi": ""
        }
      ]
    },
    {
      "id": 8,
      "chinese": "前途",
      "pinyin": "qiántú",
      "en": "future; prospects",
      "vi": "tiền đồ; tương lai",
      "sinoVietnamese": "",
      "samples": [
        {
          "type": "Noun",
          "meaning": "future; outlook; prospect",
          "sentence": "祝你有一個好的前途。",
          "pinyin": "zhù nǐ yǒu yīgè hǎo de qiántú.",
          "en": "Wish you have a great prospect.",
          "vi": ""
        },
        {
          "type": "Noun",
          "meaning": "future; outlook; prospect",
          "sentence": "她的政治前途還是個疑問。",
          "pinyin": "tā de zhèngzhì qiántú háishì gè yíwèn.",
          "en": "Her political future is in question.",
          "vi": ""
        }
      ]
    },
    {
      "id": 9,
      "chinese": "勸",
      "pinyin": "quàn",
      "en": "to persuade; to urge",
      "vi": "khuyên",
      "sinoVietnamese": "",
      "samples": [
        {
          "type": "Verb",
          "meaning": "urge; advise; try to persuade",
          "sentence": "我勸他，但是他不聽。",
          "pinyin": "wǒ quàn tā, dànshì tā bù tīng.",
          "en": "I advised him, but he didn't listen.",
          "vi": "Tôi đã khuyên anh ấy nhưng anh ấy không nghe."
        },
        {
          "type": "Verb",
          "meaning": "urge; advise; try to persuade",
          "sentence": "我們勸他別去了。",
          "pinyin": "wǒmen quàn tā bié qùle.",
          "en": "We advised him not to go.",
          "vi": ""
        }
      ]
    },
    {
      "id": 10,
      "chinese": "而已",
      "pinyin": "éryǐ",
      "en": "only; merely",
      "vi": "mà thôi",
      "sinoVietnamese": "",
      "samples": [
        {
          "type": "Particle",
          "meaning": "that is all; nothing more",
          "sentence": "他隻是有點纍而已。",
          "pinyin": "tā zhǐshì yǒudiǎn lèi éryǐ.",
          "en": "He's just a little tired.",
          "vi": ""
        },
        {
          "type": "Particle",
          "meaning": "that is all; nothing more",
          "sentence": "我們隻是普通朋友而已。",
          "pinyin": "wǒmen zhǐshì pǔtōng péngyou éryǐ.",
          "en": "We're just friends.",
          "vi": "Chúng tôi chỉ là những người bạn bình thường mà thôi."
        }
      ]
    },
    {
      "id": 11,
      "chinese": "民主",
      "pinyin": "mínzhǔ",
      "en": "democratic; democracy",
      "vi": "dân chủ",
      "sinoVietnamese": "",
      "samples": [
        {
          "type": "Noun",
          "meaning": "democracy; democratic rights",
          "sentence": "民主是社會進步的標誌。",
          "pinyin": "mínzhǔ shì shèhuì jìnbù de biāozhì.",
          "en": "Democracy is a sign of social progress.",
          "vi": "Dân chủ là dấu hiệu của tiến bộ xã hội."
        },
        {
          "type": "Noun",
          "meaning": "democracy; democratic rights",
          "sentence": "民主自由是人類的追求。",
          "pinyin": "mínzhǔ zìyóu shì rénlèi de zhuīqiú.",
          "en": "Democratic freedom is humanity's pursuit.",
          "vi": "Tự do dân chủ là điều nhân loại luôn hướng tới."
        }
      ]
    },
    {
      "id": 12,
      "chinese": "表達",
      "pinyin": "biǎodá",
      "en": "to express",
      "vi": "bày tỏ",
      "sinoVietnamese": "",
      "samples": [
        {
          "type": "Verb",
          "meaning": "deliver; express; show; voice; convey; communicate",
          "sentence": "這封信錶達了歉意。",
          "pinyin": "zhè fēng xìn biǎodále qiànyì.",
          "en": "This letter expressed an apology.",
          "vi": ""
        },
        {
          "type": "Verb",
          "meaning": "deliver; express; show; voice; convey; communicate",
          "sentence": "她錶達了自己的意見。",
          "pinyin": "tā biǎodále zìjǐ de yìjiàn.",
          "en": "She expressed her opinion.",
          "vi": ""
        }
      ]
    },
    {
      "id": 13,
      "chinese": "公共",
      "pinyin": "gōnggòng",
      "en": "public",
      "vi": "công cộng",
      "sinoVietnamese": "",
      "samples": [
        {
          "type": "Adjective",
          "meaning": "public; common; communal",
          "sentence": "公共衛生很重要。",
          "pinyin": "gōnggòng wèishēng hěn zhòngyào.",
          "en": "Public hygiene is very important.",
          "vi": "Vệ sinh công cộng rất quan trọng."
        },
        {
          "type": "Adjective",
          "meaning": "public; common; communal",
          "sentence": "人們遵守公共秩序。",
          "pinyin": "rénmen zūnshǒu gōnggòng zhìxù.",
          "en": "People adhere to public order.",
          "vi": "Mọi người tuân thủ trật tự công cộng."
        }
      ]
    },
    {
      "id": 14,
      "chinese": "議題",
      "pinyin": "yìtí",
      "en": "issue; topic",
      "vi": "vấn đề",
      "sinoVietnamese": "",
      "samples": [
        {
          "type": "Noun",
          "meaning": "subject under discussion; topic for discussion",
          "sentence": "會議的議題是環境保護。",
          "pinyin": "huìyì de yìtí shì huánjìng bǎohù.",
          "en": "The topic of the meeting is environmental protection.",
          "vi": "Vấn đề của cuộc họp là bảo vệ môi trường."
        },
        {
          "type": "Noun",
          "meaning": "subject under discussion; topic for discussion",
          "sentence": "會議上提齣了很多新的議題。",
          "pinyin": "huìyì shàng tíchūle hěnduō xīn de yìtí.",
          "en": "Many new topics were raised at the meeting.",
          "vi": "Trong cuộc họp đã đưa ra rất nhiều vấn đề mới."
        }
      ]
    },
    {
      "id": 15,
      "chinese": "核能",
      "pinyin": "hénéng",
      "en": "nuclear power",
      "vi": "năng lượng hạt nhân",
      "sinoVietnamese": "",
      "samples": [
        {
          "type": "Noun",
          "meaning": "nuclear energy",
          "sentence": "核/覈能是一種清潔能源。",
          "pinyin": "hénéng shì yī zhǒng qīngjié néngyuán.",
          "en": "Nuclear energy is a kind of clean energy.",
          "vi": "Năng lượng hạt nhân là một dạng năng lượng sạch."
        },
        {
          "type": "Noun",
          "meaning": "nuclear energy",
          "sentence": "核/覈能在軍事上也有應用。",
          "pinyin": "hénéng zài jūnshì shàng yěyǒu yìngyòng.",
          "en": "Nuclear energy is also used in the military.",
          "vi": "Năng lượng hạt nhân cũng có ứng dụng trong quân sự."
        }
      ]
    },
    {
      "id": 16,
      "chinese": "電廠",
      "pinyin": "diànchǎng",
      "en": "power plant",
      "vi": "nhà máy điện",
      "sinoVietnamese": "",
      "samples": [
        {
          "type": "Noun",
          "meaning": "electric power plant",
          "sentence": "他在縣裡/裏的電廠上班。",
          "pinyin": "Tā zài xiàn lǐ de diàn chǎng shàngbān.",
          "en": "He works at the county power plant.",
          "vi": ""
        },
        {
          "type": "colloquial",
          "meaning": "(electric) power plant; power station",
          "sentence": "火力髮/發電廠每天工作十小時。",
          "pinyin": "Huǒlì fādiàn chǎng měitiān gōngzuò shí xiǎoshí.",
          "en": "The thermal power plant works ten hours every day.",
          "vi": ""
        }
      ]
    },
    {
      "id": 17,
      "chinese": "由",
      "pinyin": "yóu",
      "en": "by; to be decided by",
      "vi": "do; bởi",
      "sinoVietnamese": "",
      "samples": [
        {
          "type": "Noun",
          "meaning": "cause; reason",
          "sentence": "事情的原由很復雜。",
          "pinyin": "shìqíng de yuányóu hěn fùzá.",
          "en": "The cause of the matter is very complicated.",
          "vi": "Nguyên nhân của sự việc rất phức tạ"
        },
        {
          "type": "Noun",
          "meaning": "cause; reason",
          "sentence": "他講述了事故的由。",
          "pinyin": "tā jiǎng shù le shìgù de yóu.",
          "en": "He explained the cause of the accident.",
          "vi": "Anh ấy kể về nguyên nhân của vụ tai nạn."
        }
      ]
    },
    {
      "id": 18,
      "chinese": "專家",
      "pinyin": "zhuānjiā",
      "en": "expert; specialist",
      "vi": "chuyên gia",
      "sinoVietnamese": "",
      "samples": [
        {
          "type": "Noun",
          "meaning": "expert; specialist; proficient",
          "sentence": "專傢對這幅畫估價很高。",
          "pinyin": "zhuānjiā duì zhè fú huà gūjià hěn gāo.",
          "en": "Experts set a high valuation on the painting.",
          "vi": ""
        },
        {
          "type": "Noun",
          "meaning": "expert; specialist; proficient",
          "sentence": "我們將需要專傢的意見。",
          "pinyin": "wǒmen jiāng xūyào zhuānjiā de yìjiàn.",
          "en": "We'll need an expert opinion.",
          "vi": ""
        }
      ]
    },
    {
      "id": 19,
      "chinese": "全面",
      "pinyin": "quánmiàn",
      "en": "comprehensive; all-around",
      "vi": "toàn diện",
      "sinoVietnamese": "",
      "samples": [
        {
          "type": "Adjective",
          "meaning": "overall; all-round",
          "sentence": "這是全麵的計劃。",
          "pinyin": "zhè shì quánmiàn de jìhuà.",
          "en": "This is a comprehensive plan.",
          "vi": "Đây là kế hoạch toàn diện."
        },
        {
          "type": "Adjective",
          "meaning": "overall; all-round",
          "sentence": "她的知識很全麵。",
          "pinyin": "tā de zhī shi hěn quánmiàn.",
          "en": "Her knowledge is very comprehensive.",
          "vi": "Kiến thức của cô ấy rất toàn diện."
        }
      ]
    },
    {
      "id": 20,
      "chinese": "民意",
      "pinyin": "mínyì",
      "en": "public opinion; the will of the people",
      "vi": "dân ý",
      "sinoVietnamese": "",
      "samples": [
        {
          "type": "noun",
          "meaning": "will of the people; popular will",
          "sentence": "民意需要認真傾聽。",
          "pinyin": "mín yì xū yào rèn zhēn qīng tīng",
          "en": "The will of the people needs to be listened to carefully.",
          "vi": ""
        },
        {
          "type": "noun",
          "meaning": "public opinion",
          "sentence": "因為他們知道這樣可以讓民意背離我們。",
          "pinyin": "yīnwèi tāmen zhīdào zhèyáng kěyǐ ràng mínyì bèilí wǒmen",
          "en": "Because they knew it would turn public opinion against us.",
          "vi": ""
        }
      ]
    },
    {
      "id": 21,
      "chinese": "代表",
      "pinyin": "dàibiǎo",
      "en": "representative; to represent",
      "vi": "đại diện",
      "sinoVietnamese": "",
      "samples": [
        {
          "type": "Noun",
          "meaning": "deputy; delegate; representative",
          "sentence": "他是公司的職工代錶。",
          "pinyin": "tā shì gōngsī de zhígōng dàibiǎo.",
          "en": "He is the employee representative of the company.",
          "vi": "Anh ấy là đại diện của nhân viên công ty."
        },
        {
          "type": "Noun",
          "meaning": "deputy; delegate; representative",
          "sentence": "這次會議選齣了30名代錶。",
          "pinyin": "zhè cì huìyì xuǎn chūle 30 míng dàibiǎo.",
          "en": "This meeting elected 30 representatives.",
          "vi": ""
        }
      ]
    },
    {
      "id": 22,
      "chinese": "處理",
      "pinyin": "chǔlǐ",
      "en": "to handle; to deal with",
      "vi": "xử lý",
      "sinoVietnamese": "",
      "samples": [
        {
          "type": "Verb",
          "meaning": "handle; deal with; dispose of",
          "sentence": "怎麼處理這個問題？",
          "pinyin": "zěnme chǔlǐ zhège wèntí?",
          "en": "How do we handle this problem?",
          "vi": ""
        },
        {
          "type": "Verb",
          "meaning": "handle; deal with; dispose of",
          "sentence": "每天至少要處理五份文件。",
          "pinyin": "měitiān zhìshǎo yào chǔlǐ wǔ fèn wénjiàn.",
          "en": "At least five documents need to be processed every day.",
          "vi": "Ít nhất năm tài liệu phải được xử lý mỗi ngày."
        }
      ]
    },
    {
      "id": 23,
      "chinese": "政黨",
      "pinyin": "zhèngdǎng",
      "en": "political party",
      "vi": "đảng phái chính trị",
      "sinoVietnamese": "",
      "samples": [
        {
          "type": "Noun",
          "meaning": "political party",
          "sentence": "這個國傢有多個政黨競爭。",
          "pinyin": "zhège guójiā yǒu duō gè zhèngdǎng jìngzhēng.",
          "en": "This country has multiple political parties competing.",
          "vi": ""
        },
        {
          "type": "Noun",
          "meaning": "political party",
          "sentence": "政黨需要製定清晰的政策。",
          "pinyin": "zhèngdǎng xūyào zhìdìng qīngxī de zhèngcè.",
          "en": "Political parties need to formulate clear policies.",
          "vi": ""
        }
      ]
    },
    {
      "id": 24,
      "chinese": "難道",
      "pinyin": "nándào",
      "en": "could it be that...?",
      "vi": "chẳng lẽ",
      "sinoVietnamese": "",
      "samples": [
        {
          "type": "Adverb",
          "meaning": "don't tell me...; could it be that...?",
          "sentence": "難道你不知道嗎？",
          "pinyin": "nándào nǐ bù zhīdào ma?",
          "en": "Could it be that you don't know?",
          "vi": ""
        },
        {
          "type": "Adverb",
          "meaning": "don't tell me...; could it be that...?",
          "sentence": "難道你不相信我？",
          "pinyin": "nándào nǐ bù xiāngxìn wǒ?",
          "en": "Could it be that you don't believe me?",
          "vi": ""
        }
      ]
    },
    {
      "id": 25,
      "chinese": "滿",
      "pinyin": "mǎn",
      "en": "to become filled with; to be dissatisfied with",
      "vi": "không hài lòng",
      "sinoVietnamese": "",
      "samples": [
        {
          "type": "Adjective",
          "meaning": "full; filled; packed",
          "sentence": "汽油罐已經加滿了油。",
          "pinyin": "qìyóu guàn yǐjīng jiā mǎnle yóu.",
          "en": "The gas tank has already been filled up.",
          "vi": "Bình xăng đã đổ đầy rồi."
        },
        {
          "type": "Adjective",
          "meaning": "all; entire; whole",
          "sentence": "他滿身是血地迴來了。",
          "pinyin": "tā mǎn shēn shì xuè de huíláile.",
          "en": "He came back covered in blood.",
          "vi": ""
        }
      ]
    },
    {
      "id": 26,
      "chinese": "憲法",
      "pinyin": "xiànfǎ",
      "en": "constitution",
      "vi": "hiến pháp",
      "sinoVietnamese": "",
      "samples": [
        {
          "type": "Noun",
          "meaning": "Constitution",
          "sentence": "法官必須依據憲法判案。",
          "pinyin": "fǎguān bìxū yījù xiànfǎ pàn àn.",
          "en": "Judges must rule according to the Constitution.",
          "vi": ""
        },
        {
          "type": "Noun",
          "meaning": "Constitution",
          "sentence": "憲法對政府行為有約束力。",
          "pinyin": "xiànfǎ duì zhèngfǔ xíngwéi yǒu yuēshù lì.",
          "en": "The Constitution restricts government actions.",
          "vi": ""
        }
      ]
    },
    {
      "id": 27,
      "chinese": "投票權",
      "pinyin": "tóupiàoquán",
      "en": "the right to vote",
      "vi": "quyền bầu cử",
      "sinoVietnamese": "",
      "samples": [
        {
          "type": "Noun",
          "meaning": "right to vote",
          "sentence": "女性的投票權。",
          "pinyin": "nv̌xìng de tóupiàoquán",
          "en": "There goes the right to vote.",
          "vi": "Có quyền bỏ phiếu."
        }
      ]
    },
    {
      "id": 28,
      "chinese": "選舉",
      "pinyin": "xuǎnjǔ",
      "en": "election",
      "vi": "bầu cử",
      "sinoVietnamese": "",
      "samples": [
        {
          "type": "Verb",
          "meaning": "vote; elect",
          "sentence": "村民們選舉了新的村長。",
          "pinyin": "cūnmínmen xuǎnjǔle xīn de cūn zhǎng.",
          "en": "The villagers have elected a new village head.",
          "vi": "Người dân trong làng đã bầu ra trưởng thôn mới."
        },
        {
          "type": "Verb",
          "meaning": "vote; elect",
          "sentence": "他們正在選舉新班長。",
          "pinyin": "tāmen zhèngzài xuǎnjǔ xīn bānzhǎng.",
          "en": "They are electing a new class monitor.",
          "vi": ""
        }
      ]
    },
    {
      "id": 29,
      "chinese": "權利",
      "pinyin": "quánlì",
      "en": "right",
      "vi": "quyền lợi; quyền",
      "sinoVietnamese": "",
      "samples": [
        {
          "type": "Noun",
          "meaning": "right; interest",
          "sentence": "權利包含著義務。",
          "pinyin": "quánlì bāohánzhe yìwù.",
          "en": "Rights come with responsibilities.",
          "vi": "Quyền lợi đi đôi với nghĩa vụ."
        },
        {
          "type": "Noun",
          "meaning": "right; interest",
          "sentence": "他放棄了繼承權利。",
          "pinyin": "tā fàngqìle jìchéng quánlì.",
          "en": "He renounced his inheritance rights.",
          "vi": ""
        }
      ]
    },
    {
      "id": 30,
      "chinese": "表示",
      "pinyin": "biǎoshì",
      "en": "to indicate; to show",
      "vi": "biểu thị",
      "sinoVietnamese": "",
      "samples": [
        {
          "type": "Verb",
          "meaning": "show; express; indicate",
          "sentence": "他嚮我錶示感謝。",
          "pinyin": "tā xiàng wǒ biǎoshì gǎnxiè.",
          "en": "He expressed his gratitude to me.",
          "vi": "Anh ấy bày tỏ lòng biết ơn với tôi."
        },
        {
          "type": "Verb",
          "meaning": "show; express; indicate",
          "sentence": "領導嚮工人錶示慰問。",
          "pinyin": "lǐngdǎo xiàng gōngrén biǎoshì wèiwèn.",
          "en": "The leader expressed sympathy and solicitude to the workers.",
          "vi": "Lãnh đạo ngỏ lời thăm hỏi đến công nhân."
        }
      ]
    },
    {
      "id": 31,
      "chinese": "反映",
      "pinyin": "fǎnyìng",
      "en": "to reflect",
      "vi": "phản ánh",
      "sinoVietnamese": "",
      "samples": [
        {
          "type": "Verb",
          "meaning": "reflect; mirror",
          "sentence": "這部小説反映了生活。",
          "pinyin": "zhè bù xiǎoshuō fǎnyìngle shēnghuó.",
          "en": "This novel reflects life.",
          "vi": ""
        },
        {
          "type": "Verb",
          "meaning": "reflect; mirror",
          "sentence": "態度反映一個人的性格。",
          "pinyin": "tàidù fǎnyìng yīgè rén de xìnggé.",
          "en": "Attitude reflects a person's character.",
          "vi": ""
        }
      ]
    },
    {
      "id": 32,
      "chinese": "為",
      "pinyin": "wèi",
      "en": "for",
      "vi": "vì",
      "sinoVietnamese": "",
      "samples": [
        {
          "type": "Verb",
          "meaning": "do; act",
          "sentence": "我們應該儘力而為。",
          "pinyin": "wǒmen yīnggāi jìnlì ér wéi.",
          "en": "We should do our best.",
          "vi": "Chúng ta nên làm hết sức mình."
        },
        {
          "type": "Verb",
          "meaning": "do; act",
          "sentence": "這個項目大有可為。",
          "pinyin": "zhège xiàngmù dàyǒukěwéi.",
          "en": "This project has great potential.",
          "vi": "Dự án này rất đáng làm."
        }
      ]
    },
    {
      "id": 33,
      "chinese": "服務",
      "pinyin": "fúwù",
      "en": "to serve",
      "vi": "phục vụ",
      "sinoVietnamese": "",
      "samples": [
        {
          "type": "Verb",
          "meaning": "give service to; be in the service of; serve",
          "sentence": "我們的目標是服務社會。",
          "pinyin": "wǒmen de mùbiāo shì fúwù shèhuì.",
          "en": "Our goal is to serve society.",
          "vi": "Mục tiêu của chúng tôi là phục vụ xã hội."
        },
        {
          "type": "Verb",
          "meaning": "give service to; be in the service of; serve",
          "sentence": "我們緻力於服務客戶。",
          "pinyin": "wǒmen zhìlì yú fúwù kèhù.",
          "en": "We are committed to serving our customers.",
          "vi": ""
        }
      ]
    },
    {
      "id": 34,
      "chinese": "職位",
      "pinyin": "zhíwèi",
      "en": "position; post",
      "vi": "chức vụ",
      "sinoVietnamese": "",
      "samples": [
        {
          "type": "Noun",
          "meaning": "post; position",
          "sentence": "他是最適宜那個職位的人。",
          "pinyin": "tā shì zuì shìyí nàge zhíwèi de rén.",
          "en": "He is the most suitable person for that position.",
          "vi": "Anh ấy là người phù hợp nhất cho vị trí đó."
        },
        {
          "type": "Noun",
          "meaning": "post; position",
          "sentence": "新職位僅限於內部招聘。",
          "pinyin": "xīn zhíwèi jǐn xiànyú nèibù zhāopìn.",
          "en": "New positions are limited to internal recruitment.",
          "vi": "Các vị trí mới sẽ chỉ được tuyển dụng nội bộ."
        }
      ]
    },
    {
      "id": 35,
      "chinese": "任期",
      "pinyin": "rènqī",
      "en": "term of office",
      "vi": "nhiệm kỳ",
      "sinoVietnamese": "",
      "samples": [
        {
          "type": "Noun",
          "meaning": "term of office; term of service; tenure of office",
          "sentence": "他的任期已滿。",
          "pinyin": "tā de rènqī yǐ mǎn.",
          "en": "His term of office has run out.",
          "vi": ""
        },
        {
          "type": "Noun",
          "meaning": "term of office; term of service; tenure of office",
          "sentence": "全國人民代錶大會每屆任期5年。",
          "pinyin": "Quánguó rénmín dàibiǎo dàhuì měi jiè rènqī 5 nián.",
          "en": "The National People's Congress is elected for a term of five years.",
          "vi": ""
        }
      ]
    },
    {
      "id": 36,
      "chinese": "選民",
      "pinyin": "xuǎnmín",
      "en": "voter; electorate",
      "vi": "cử tri",
      "sinoVietnamese": "",
      "samples": [
        {
          "type": "Noun",
          "meaning": "voter; elector",
          "sentence": "在美國，多數選舉都安排在11月份一起舉行。這樣，一個選民隻需去選地一次。",
          "pinyin": "Zài Měiguó, duōshù xuǎnjǔ dōu ānpái zài 11 yuèfèn yīqǐ jǔxíng. Zhèyàng, yīgè xuǎnmín zhǐ xū qù xuǎndì yīcì.",
          "en": "In the United States, most of the elections are held together in November, so that a voter needs to make one visit to the voting place.",
          "vi": ""
        },
        {
          "type": "Noun",
          "meaning": "voter; elector",
          "sentence": "選民們不喜歡激進分子。",
          "pinyin": "xuǎnmín men bù xǐhuān jījìnfēnzǐ",
          "en": "Voters don't like radicals.",
          "vi": "Cử tri không thích những người cấp tiến."
        }
      ]
    },
    {
      "id": 37,
      "chinese": "完美",
      "pinyin": "wánměi",
      "en": "perfect",
      "vi": "hoàn hảo",
      "sinoVietnamese": "",
      "samples": [
        {
          "type": "Adjective",
          "meaning": "perfect; flawless; consummate",
          "sentence": "她的錶現很完美。",
          "pinyin": "tā de biǎoxiàn hěn wánměi.",
          "en": "Her performance was perfect.",
          "vi": ""
        },
        {
          "type": "Adjective",
          "meaning": "perfect; flawless; consummate",
          "sentence": "這是一個完美的計劃。",
          "pinyin": "zhè shì yīgè wánměi de jìhuà.",
          "en": "This is a perfect plan.",
          "vi": "Đây là một kế hoạch hoàn hảo."
        }
      ]
    },
    {
      "id": 38,
      "chinese": "積極",
      "pinyin": "jījí",
      "en": "actively; proactive",
      "vi": "tích cực",
      "sinoVietnamese": "",
      "samples": [
        {
          "type": "Adjective",
          "meaning": "active",
          "sentence": "衕學們的錶現很積極。",
          "pinyin": "tóngxuémen de biǎoxiàn hěn jījí.",
          "en": "The students' performance is very positive.",
          "vi": ""
        },
        {
          "type": "Adjective",
          "meaning": "active",
          "sentence": "這個員工工作很積極。",
          "pinyin": "zhège yuángōng gōngzuò hěn jījí.",
          "en": "This employee works very proactively.",
          "vi": ""
        }
      ]
    },
    {
      "id": 39,
      "chinese": "最佳",
      "pinyin": "zuìjiā",
      "en": "the best possible",
      "vi": "tốt nhất",
      "sinoVietnamese": "",
      "samples": [
        {
          "type": "Adjective",
          "meaning": "the best; optimum",
          "sentence": "這是我讀過的最佳小説。",
          "pinyin": "zhè shì wǒ dúguò de zuì jiā xiǎoshuō.",
          "en": "This is the best novel I have ever read.",
          "vi": "Đây là cuốn tiểu thuyết hay nhất tôi từng đọc."
        },
        {
          "type": "Adjective",
          "meaning": "the best; optimum",
          "sentence": "作畫的最佳時間是白天。",
          "pinyin": "zuòhuà de zuì jiā shíjiān shì báitiān.",
          "en": "The best time to paint is during the day.",
          "vi": "Thời gian tốt nhất để vẽ là ban ngày."
        }
      ]
    },
    {
      "id": 40,
      "chinese": "推銷員",
      "pinyin": "tuīxiāoyuán",
      "en": "salesperson",
      "vi": "nhân viên chào hàng",
      "sinoVietnamese": "",
      "samples": [
        {
          "type": "Noun",
          "meaning": "salesman; salesperson; sales representative",
          "sentence": "這個推銷員非常熱情。",
          "pinyin": "zhège tuīxiāo yuán fēicháng rèqíng.",
          "en": "The salesperson is very enthusiastic.",
          "vi": "Nhân viên bán hàng này rất nhiệt tình."
        },
        {
          "type": "Noun",
          "meaning": "salesman; salesperson; sales representative",
          "sentence": "這個推銷員很友好。",
          "pinyin": "zhège tuīxiāo yuán hěn yǒuhǎo.",
          "en": "The salesperson is very friendly.",
          "vi": "Nhân viên bán hàng này rất thân thiện."
        }
      ]
    },
    {
      "id": 41,
      "chinese": "有道理",
      "pinyin": "yǒu dàolǐ",
      "en": "to make sense",
      "vi": "có lý",
      "sinoVietnamese": "",
      "samples": [
        {
          "type": "Verb",
          "meaning": "reasonable; there is truth in; be well founded",
          "sentence": "你有道理，我算服了你了。",
          "pinyin": "nǐ yǒu dàolǐ, wǒ suàn fúle nǐle.",
          "en": "You make sense, I give in to you.",
          "vi": "Anh có lý, tôi hoàn toàn tin anh."
        },
        {
          "type": "Verb",
          "meaning": "reasonable; there is truth in; be well founded",
          "sentence": "你的想法有道理，我衕意。",
          "pinyin": "nǐ de xiǎngfǎ yǒu dàolǐ, wǒ tóngyì.",
          "en": "Your idea makes sense, I agree.",
          "vi": "Tôi đồng ý, ý tưởng của bạn có lý."
        }
      ]
    },
    {
      "id": 42,
      "chinese": "候選人",
      "pinyin": "hòuxuǎnrén",
      "en": "candidate",
      "vi": "ứng cử viên",
      "sinoVietnamese": "",
      "samples": [
        {
          "type": "Noun",
          "meaning": "candidate",
          "sentence": "他是這次比賽的候選人之一。",
          "pinyin": "tā shì zhè cì bǐsài de hòuxuǎn rén zhī yī.",
          "en": "He is one of the candidates for this competition.",
          "vi": "Anh ấy là một trong những ứng cử viên của cuộc thi này."
        },
        {
          "type": "Noun",
          "meaning": "candidate",
          "sentence": "他是最有可能穫勝的候選人。",
          "pinyin": "tā shì zuì yǒu kěnéng huòshèng de hòuxuǎn rén.",
          "en": "He is the candidate most likely to win.",
          "vi": "Anh ấy là ứng cử viên có khả năng chiến thắng cao nhất."
        }
      ]
    },
    {
      "id": 43,
      "chinese": "學術界",
      "pinyin": "xuéshùjiè",
      "en": "academic circles",
      "vi": "giới học thuật",
      "sinoVietnamese": "",
      "samples": [
        {
          "type": "Noun",
          "meaning": "academia",
          "sentence": "嫌犯可能是學術界一員。",
          "pinyin": "xiánfàn kěnéng shì xuéshùjiè yì yuán.",
          "en": "The unsub may be a part of academia.",
          "vi": ""
        },
        {
          "type": "Noun",
          "meaning": "academia",
          "sentence": "他在學術界很有聲望。",
          "pinyin": "tā zài xuéshù jiè hěn yǒu shēngwàng.",
          "en": "He is highly reputable in academia.",
          "vi": ""
        }
      ]
    },
    {
      "id": 44,
      "chinese": "從政",
      "pinyin": "cóngzhèng",
      "en": "to go into politics",
      "vi": "tham gia chính trị",
      "sinoVietnamese": "",
      "samples": [
        {
          "type": "Preposition",
          "meaning": "from (a time, a place, or a point of view)",
          "sentence": "她從懷裡/裏掏齣一塊帨。",
          "pinyin": "Tā cóng huái lǐ tāo chū yī kuài shuì.",
          "en": "She took out a piece of cloth from her bosom.",
          "vi": ""
        },
        {
          "type": "Preposition",
          "meaning": "from (a time, a place, or a point of view)",
          "sentence": "另一個從科羅拉多打過去的。",
          "pinyin": "lìng yīgè cóng kēluōlāduō dǎ guòqù de",
          "en": "The other is from Colorado.",
          "vi": ""
        }
      ]
    },
    {
      "id": 45,
      "chinese": "政策",
      "pinyin": "zhèngcè",
      "en": "policy",
      "vi": "chính sách",
      "sinoVietnamese": "",
      "samples": [
        {
          "type": "Noun",
          "meaning": "policy",
          "sentence": "公司的政策很嚴格。",
          "pinyin": "gōngsī de zhèngcè hěn yángé.",
          "en": "The company's policy is very strict.",
          "vi": "Chính sách của công ty rất nghiêm ngặt."
        },
        {
          "type": "Noun",
          "meaning": "policy",
          "sentence": "我們討論了公司的新政策。",
          "pinyin": "wǒmen tǎolùnle gōngsī de xīn zhèngcè.",
          "en": "We discussed the company's new policy.",
          "vi": ""
        }
      ]
    },
    {
      "id": 46,
      "chinese": "安定",
      "pinyin": "āndìng",
      "en": "stable; peaceful",
      "vi": "ổn định",
      "sinoVietnamese": "",
      "samples": [
        {
          "type": "Adjective",
          "meaning": "stable; quiet; settled; peaceful and in order",
          "sentence": "我們需要一個安定的環境。",
          "pinyin": "wǒmen xūyào yīgè āndìng de huánjìng.",
          "en": "We need a stable environment.",
          "vi": "Chúng ta cần một môi trường ổn định."
        },
        {
          "type": "Adjective",
          "meaning": "stable; quiet; settled; peaceful and in order",
          "sentence": "安定的社會促進經濟髮/發展。",
          "pinyin": "āndìng de shèhuì cùjìn jīngjì fāzhǎn.",
          "en": "A stable society promotes economic development.",
          "vi": "Xã hội ổn định thúc đẩy kinh tế phát triển."
        }
      ]
    },
    {
      "id": 47,
      "chinese": "辭",
      "pinyin": "cí",
      "en": "to resign; to quit",
      "vi": "từ chức; nghỉ việc",
      "sinoVietnamese": "",
      "samples": [
        {
          "type": "noun",
          "meaning": "diction; phraseology",
          "sentence": "他擅長寫辭。",
          "pinyin": "tā shàncháng xiě cí.",
          "en": "He is skilled at writing lyrics.",
          "vi": "Anh ấy giỏi viết văn từ."
        },
        {
          "type": "noun",
          "meaning": "diction; phraseology",
          "sentence": "古代的辭具有魅力。",
          "pinyin": "gǔdài de cí jùyǒu mèilì.",
          "en": "Ancient Chinese poetry is captivating.",
          "vi": "Văn từ thời cổ đại có sức hấp dẫn."
        }
      ]
    },
    {
      "id": 48,
      "chinese": "頭腦",
      "pinyin": "tóunǎo",
      "en": "mind; brain",
      "vi": "đầu óc",
      "sinoVietnamese": "",
      "samples": [
        {
          "type": "Noun",
          "meaning": "brains; mind",
          "sentence": "他的頭腦非常聰明。",
          "pinyin": "tā de tóunǎo fēicháng cōngmíng.",
          "en": "His mind is very smart.",
          "vi": ""
        },
        {
          "type": "Noun",
          "meaning": "brains; mind",
          "sentence": "他被戀愛衝昏了頭腦。",
          "pinyin": "tā bèi liàn'ài chōng hūnle tóunǎo.",
          "en": "She was carried away by love.",
          "vi": ""
        }
      ]
    },
    {
      "id": 49,
      "chinese": "改革",
      "pinyin": "gǎigé",
      "en": "reform",
      "vi": "cải cách",
      "sinoVietnamese": "",
      "samples": [
        {
          "type": "Verb",
          "meaning": "to reform",
          "sentence": "這個國傢在進行改革。",
          "pinyin": "zhège guójiā zài jìnxíng gǎigé.",
          "en": "This country is undergoing reforms.",
          "vi": ""
        },
        {
          "type": "Verb",
          "meaning": "to reform",
          "sentence": "我要改革現有的製度。",
          "pinyin": "wǒ yào gǎigé xiàn yǒu de zhìdù.",
          "en": "I aim to reform the current system.",
          "vi": ""
        }
      ]
    },
    {
      "id": 50,
      "chinese": "看法",
      "pinyin": "kànfǎ",
      "en": "view; opinion",
      "vi": "cách nhìn; quan điểm",
      "sinoVietnamese": "",
      "samples": [
        {
          "type": "Noun",
          "meaning": "opinion; perspective; (point of) view; a way of looking at a thing",
          "sentence": "我們需要交換看法。",
          "pinyin": "wǒmen xūyào jiāohuàn kànfǎ.",
          "en": "We need to exchange opinions.",
          "vi": "Chúng ta cần trao đổi ý kiến."
        },
        {
          "type": "Noun",
          "meaning": "opinion; perspective; (point of) view; a way of looking at a thing",
          "sentence": "請談談你的看法。",
          "pinyin": "qǐng tántan nǐ de kànfǎ.",
          "en": "Please tell us your opinion.",
          "vi": ""
        }
      ]
    },
    {
      "id": 51,
      "chinese": "教育",
      "pinyin": "jiàoyù",
      "en": "education",
      "vi": "giáo dục",
      "sinoVietnamese": "",
      "samples": [
        {
          "type": "Noun",
          "meaning": "education",
          "sentence": "教育是社會進步的基石。",
          "pinyin": "jiàoyù shì shèhuì jìnbù de jīshí.",
          "en": "Education is the cornerstone of social progress.",
          "vi": "Giáo dục là nền tảng của sự tiến bộ xã hội."
        },
        {
          "type": "Noun",
          "meaning": "education",
          "sentence": "政府增加了教育的投入。",
          "pinyin": "zhèngfǔ zēngjiāle jiàoyù de tóurù.",
          "en": "The government has increased investment in education.",
          "vi": "Chính phủ đã tăng cường đầu tư vào giáo dục."
        }
      ]
    },
    {
      "id": 52,
      "chinese": "方面",
      "pinyin": "fāngmiàn",
      "en": "aspect; area",
      "vi": "phương diện",
      "sinoVietnamese": "",
      "samples": [
        {
          "type": "Noun",
          "meaning": "side; field; aspect; respect",
          "sentence": "這個問題有很多方麵。",
          "pinyin": "zhège wèntí yǒu hěnduō fāngmiàn.",
          "en": "This problem has many aspects.",
          "vi": "Có nhiều khía cạnh cho vấn đề này."
        },
        {
          "type": "Noun",
          "meaning": "side; field; aspect; respect",
          "sentence": "我們討論了很多方麵。",
          "pinyin": "wǒmen tǎolùnle hěnduō fāngmiàn.",
          "en": "We discussed many sides.",
          "vi": "Chúng tôi đã thảo luận nhiều mặt."
        }
      ]
    },
    {
      "id": 53,
      "chinese": "得到",
      "pinyin": "dédào",
      "en": "to obtain; to receive",
      "vi": "nhận được",
      "sinoVietnamese": "",
      "samples": [
        {
          "type": "Verb",
          "meaning": "get; obtain; gain; receive",
          "sentence": "我得到了老師的錶揚。",
          "pinyin": "wǒ dédàole lǎoshī de biǎoyáng.",
          "en": "I got the praise of the teacher.",
          "vi": ""
        },
        {
          "type": "Verb",
          "meaning": "get; obtain; gain; receive",
          "sentence": "他得到了優秀員工的稱號。",
          "pinyin": "tā dédàole yōuxiù yuángōng de chēnghào.",
          "en": "He got the title of excellent employee.",
          "vi": ""
        }
      ]
    },
    {
      "id": 54,
      "chinese": "連任",
      "pinyin": "liánrèn",
      "en": "to be re-elected; to serve a successive term",
      "vi": "tái đắc cử",
      "sinoVietnamese": "",
      "samples": [
        {
          "type": "Verb",
          "meaning": "be reappointed or re-elected consecutively; renew one's term of office",
          "sentence": "連任部長",
          "pinyin": "liánrèn bùzhǎng",
          "en": "Be reappointed minister",
          "vi": ""
        },
        {
          "type": "Verb",
          "meaning": "be reappointed or re-elected consecutively; renew one's term of office",
          "sentence": "連任總統",
          "pinyin": "liánrèn zǒngtǒng",
          "en": "Be re-elected president",
          "vi": ""
        }
      ]
    },
    {
      "id": 55,
      "chinese": "屆",
      "pinyin": "jiè",
      "en": "term of office",
      "vi": "nhiệm kỳ",
      "sinoVietnamese": "",
      "samples": [
        {
          "type": "Verb",
          "meaning": "fall due",
          "sentence": "屆時你會明白。",
          "pinyin": "jièshí nǐ huì míngbái.",
          "en": "You will understand then.",
          "vi": "Đến lúc đó bạn sẽ hiểu."
        },
        {
          "type": "Verb",
          "meaning": "fall due",
          "sentence": "屆期馬上到了。",
          "pinyin": "Jièqī mǎshàng dàole.",
          "en": "The due date is almost here.",
          "vi": "Kỳ hạn sắp đến rồi."
        }
      ]
    },
    {
      "id": 56,
      "chinese": "支持度",
      "pinyin": "zhīchídù",
      "en": "approval rating",
      "vi": "mức độ ủng hộ",
      "sinoVietnamese": "",
      "samples": [
        {
          "type": "Noun",
          "meaning": "degree of support",
          "sentence": "民眾/衆對政府的支持度提高。",
          "pinyin": "Mín zhòng duì zhèng fǔ de zhī chí dù tí gāo.",
          "en": "Public support for the government increased.",
          "vi": ""
        },
        {
          "type": "Noun",
          "meaning": "percentage of vote",
          "sentence": "選民的支持度在上昇。",
          "pinyin": "xuǎn mín de zhī chí dù zài shàng shēng",
          "en": "The voters' support rating is rising.",
          "vi": ""
        }
      ]
    },
    {
      "id": 57,
      "chinese": "落選",
      "pinyin": "luòxuǎn",
      "en": "to lose an election",
      "vi": "trượt cử",
      "sinoVietnamese": "",
      "samples": [
        {
          "type": "Verb",
          "meaning": "fail to be chosen; lose an election (opp. 入选, 当选)",
          "sentence": "他在選舉中意外落選了。",
          "pinyin": "Tā zài xuǎnjǔ zhōng yìwài luòxuǎn le.",
          "en": "He unexpectedly lost in the election.",
          "vi": ""
        },
        {
          "type": "Verb",
          "meaning": "to fail to be chosen (or elected)",
          "sentence": "他最後一次落選了。",
          "pinyin": "tā zuì hòu yí cì luò xuǎn le",
          "en": "He ended up not being selected.",
          "vi": ""
        }
      ]
    },
    {
      "id": 58,
      "chinese": "得票率",
      "pinyin": "dépiàolǜ",
      "en": "percentage of votes received",
      "vi": "tỷ lệ phiếu bầu",
      "sinoVietnamese": "",
      "samples": [
        {
          "type": "Noun",
          "meaning": "percentage of votes obtained",
          "sentence": "他的得票率很高。",
          "pinyin": "Tā de dépiào lǜ hěn gāo.",
          "en": "His vote rate is very high.",
          "vi": "Tỷ lệ phiếu của anh ấy rất cao."
        }
      ]
    },
    {
      "id": 59,
      "chinese": "預期",
      "pinyin": "yùqí",
      "en": "expectation",
      "vi": "dự kiến; kỳ vọng",
      "sinoVietnamese": "",
      "samples": [
        {
          "type": "Verb",
          "meaning": "expect; anticipate; envision",
          "sentence": "我們預期明天會下雨。",
          "pinyin": "wǒmen yùqī míngtiān huì xiàyǔ.",
          "en": "We expect it to rain tomorrow.",
          "vi": "Chúng tôi dự kiến ngày mai sẽ mưa."
        },
        {
          "type": "Verb",
          "meaning": "expect; anticipate; envision",
          "sentence": "公司預期銷售額會增加。",
          "pinyin": "gōngsī yùqī xiāoshòu é huì zēngjiā.",
          "en": "The company anticipates an increase in sales.",
          "vi": ""
        }
      ]
    },
    {
      "id": 60,
      "chinese": "暫時",
      "pinyin": "zhànshí",
      "en": "temporarily; for the time being",
      "vi": "tạm thời",
      "sinoVietnamese": "",
      "samples": [
        {
          "type": "Adjective",
          "meaning": "transient; temporary; for the time being",
          "sentence": "我暫時不想吃/喫。",
          "pinyin": "wǒ zànshí bùxiǎng chī.",
          "en": "I don't want to eat for the time being.",
          "vi": ""
        },
        {
          "type": "Adjective",
          "meaning": "transient; temporary; for the time being",
          "sentence": "我暫時不想去旅行。",
          "pinyin": "wǒ zànshí bùxiǎng qù lǚxíng.",
          "en": "I don't want to travel for the time being.",
          "vi": "Tớ tạm thời không muốn đi du lịch."
        }
      ]
    },
    {
      "id": 61,
      "chinese": "老家",
      "pinyin": "lǎojiā",
      "en": "hometown; old home",
      "vi": "quê nhà",
      "sinoVietnamese": "",
      "samples": [
        {
          "type": "Noun",
          "meaning": "hometown; native place",
          "sentence": "我好久沒迴老傢了。",
          "pinyin": "wǒ hǎojiǔ méi huílǎojiāle.",
          "en": "I haven't been back to my hometown for a long time.",
          "vi": "Lâu lắm tôi chưa về quê rồi."
        },
        {
          "type": "Noun",
          "meaning": "hometown; native place",
          "sentence": "春節我要迴趟老傢。",
          "pinyin": "chūnjié wǒ yào huí tàng lǎojiā.",
          "en": "I will go back to my hometown during the Spring Festival.",
          "vi": ""
        }
      ]
    },
    {
      "id": 62,
      "chinese": "形象",
      "pinyin": "xíngxiàng",
      "en": "image",
      "vi": "hình tượng; hình ảnh",
      "sinoVietnamese": "",
      "samples": [
        {
          "type": "Noun",
          "meaning": "image; form; figure",
          "sentence": "藝術傢的形象非常獨特。",
          "pinyin": "yìshùjiā de xíngxiàng fēicháng dútè.",
          "en": "The artist's image is one of a kind.",
          "vi": "Hình ảnh của nghệ sĩ rất độc đáo."
        },
        {
          "type": "Noun",
          "meaning": "image; form; figure",
          "sentence": "他破壞了自己的公眾/衆形象。",
          "pinyin": "tā pòhuàile zìjǐ de gōngzhòng xíngxiàng.",
          "en": "He severely damaged his public image.",
          "vi": "Anh ấy đã hủy hoại hình ảnh công chúng của mình."
        }
      ]
    },
    {
      "id": 63,
      "chinese": "商量",
      "pinyin": "shāngliáng",
      "en": "to discuss; to consult",
      "vi": "bàn bạc",
      "sinoVietnamese": "",
      "samples": [
        {
          "type": "Verb",
          "meaning": "consult; discuss; talk over",
          "sentence": "這件事需要好好商量。",
          "pinyin": "zhè jiàn shì xūyào hǎohǎo shāngliang.",
          "en": "This matter needs to be discussed thoroughly.",
          "vi": "Việc này cần được bàn bạc kỹ lưỡng."
        },
        {
          "type": "Verb",
          "meaning": "consult; discuss; talk over",
          "sentence": "你和他商量過了嗎？",
          "pinyin": "nǐ hé tā shāngliangguòle ma?",
          "en": "Have you discussed it with him?",
          "vi": "Bạn đã bàn bạc với anh ấy chưa?"
        }
      ]
    },
    {
      "id": 64,
      "chinese": "人脈",
      "pinyin": "rénmài",
      "en": "network of contacts",
      "vi": "quan hệ; mạng lưới quan hệ",
      "sinoVietnamese": "",
      "samples": [
        {
          "type": "Noun",
          "meaning": "connections; social relationship",
          "sentence": "人脈在商業中很重要。",
          "pinyin": "rénmài zài shāngyè zhōng hěn zhòngyào.",
          "en": "Connections are very important in business.",
          "vi": "Mối quan hệ rất quan trọng trong kinh doanh."
        },
        {
          "type": "Noun",
          "meaning": "connections; social relationship",
          "sentence": "她利用人脈找到了工作。",
          "pinyin": "tā lìyòng rénmài zhǎodàole gōngzuò.",
          "en": "She used her connections to find a job.",
          "vi": "Cô ấy dùng mối quan hệ để tìm việc."
        }
      ]
    },
    {
      "id": 65,
      "chinese": "弱勢",
      "pinyin": "ruòshì",
      "en": "disadvantaged",
      "vi": "yếu thế",
      "sinoVietnamese": "",
      "samples": [
        {
          "type": "Noun",
          "meaning": "a down trend",
          "sentence": "這個行業正處於弱勢期。",
          "pinyin": "zhège hángyè zhèng chǔyú ruòshì qī.",
          "en": "This industry is in a downturn.",
          "vi": "Ngành này hiện đang trong giai đoạn suy yếu."
        },
        {
          "type": "Noun",
          "meaning": "a down trend",
          "sentence": "這支隊伍的錶現處於弱勢。",
          "pinyin": "zhè zhī duìwǔ de biǎoxiàn chǔyú ruòshì.",
          "en": "This team's performance is declining.",
          "vi": ""
        }
      ]
    },
    {
      "id": 66,
      "chinese": "退休",
      "pinyin": "tuìxiū",
      "en": "to retire",
      "vi": "nghỉ hưu",
      "sinoVietnamese": "",
      "samples": [
        {
          "type": "Verb",
          "meaning": "retire",
          "sentence": "我已經退休三年了。",
          "pinyin": "wǒ yǐjīng tuìxiū sān niánle.",
          "en": "I have been retired for three years.",
          "vi": "Tôi đã nghỉ hưu được ba năm rồi."
        },
        {
          "type": "Verb",
          "meaning": "retire",
          "sentence": "爺爺已經退休多年。",
          "pinyin": "yéye yǐjīng tuìxiū duōnián.",
          "en": "Grandpa has been retired for many years.",
          "vi": ""
        }
      ]
    },
    {
      "id": 67,
      "chinese": "事業",
      "pinyin": "shìyè",
      "en": "business; career",
      "vi": "sự nghiệp; cơ nghiệp",
      "sinoVietnamese": "",
      "samples": [
        {
          "type": "Noun",
          "meaning": "cause; career; enterprise; undertaking",
          "sentence": "他專註於自己的事業。",
          "pinyin": "tā zhuānzhù yú zìjǐ de shìyè.",
          "en": "He focuses on his career.",
          "vi": "Anh ấy tập trung vào sự nghiệp của mình."
        },
        {
          "type": "Noun",
          "meaning": "cause; career; enterprise; undertaking",
          "sentence": "他事業上遇到了挑戰。",
          "pinyin": "tā shìyè shàng yùdàole tiǎozhàn.",
          "en": "He is encountering difficulties in his career.",
          "vi": "Anh ấy gặp phải thử thách trong sự nghiệp."
        }
      ]
    },
    {
      "id": 68,
      "chinese": "捐",
      "pinyin": "juān",
      "en": "to donate",
      "vi": "quyên góp; hiến tặng",
      "sinoVietnamese": "",
      "samples": [
        {
          "type": "verb",
          "meaning": "sacrifice; contribute",
          "sentence": "他為了國傢捐軀。",
          "pinyin": "tā wèile guójiā juānqū.",
          "en": "He sacrificed his life for his country.",
          "vi": "Anh ấy hy sinh vì tổ quốc."
        },
        {
          "type": "verb",
          "meaning": "sacrifice; contribute",
          "sentence": "英雄無畏地捐齣自己。",
          "pinyin": "yīngxióng wúwèi de juān chū zìjǐ.",
          "en": "Heroes selflessly donated themselves.",
          "vi": "Anh hùng dũng cảm hiến dâng chính mình."
        }
      ]
    },
    {
      "id": 69,
      "chinese": "義務",
      "pinyin": "yìwù",
      "en": "to volunteer; volunteer basis",
      "vi": "tình nguyện",
      "sinoVietnamese": "",
      "samples": [
        {
          "type": "Noun",
          "meaning": "duty; obligation",
          "sentence": "遵守法律是公民的義務。",
          "pinyin": "zūnshǒu fǎlǜ shì gōngmín de yìwù.",
          "en": "It is the duty of citizens to obey the law.",
          "vi": ""
        },
        {
          "type": "Noun",
          "meaning": "duty; obligation",
          "sentence": "我們有義務關懷這些難民。",
          "pinyin": "wǒmen yǒu yìwù guānhuái zhèxiē nánmín.",
          "en": "We have a duty to care for the refugees.",
          "vi": ""
        }
      ]
    },
    {
      "id": 70,
      "chinese": "經費",
      "pinyin": "jīngfèi",
      "en": "funds",
      "vi": "kinh phí",
      "sinoVietnamese": "",
      "samples": [
        {
          "type": "Noun",
          "meaning": "funds; budget",
          "sentence": "學校的經費不夠。",
          "pinyin": "xuéxiào de jīngfèi bùgòu.",
          "en": "The school’s funds are insufficient.",
          "vi": "Kinh phí của trường không đủ."
        },
        {
          "type": "Noun",
          "meaning": "funds; budget",
          "sentence": "他負責管理經費。",
          "pinyin": "tā fùzé guǎnlǐ jīngfèi.",
          "en": "He is responsible for managing the budget.",
          "vi": "Anh ấy phụ trách quản lý kinh phí."
        }
      ]
    },
    {
      "id": 71,
      "chinese": "競選",
      "pinyin": "jìngxuǎn",
      "en": "to run for office",
      "vi": "tranh cử",
      "sinoVietnamese": "",
      "samples": [
        {
          "type": "Verb",
          "meaning": "enter into an election contest; campaign for (office); run for",
          "sentence": "競選總統",
          "pinyin": "jìng xuǎn zǒng tǒng",
          "en": "Run for the presidency",
          "vi": ""
        },
        {
          "type": "Verb",
          "meaning": "enter into an election contest; campaign for (office); run for",
          "sentence": "我被邀請參加總統競選了。",
          "pinyin": "wǒ bèi yāoqǐng cānjiā zǒngtǒng jìngxuǎn le",
          "en": "I've been asked to run for president.",
          "vi": ""
        }
      ]
    },
    {
      "id": 72,
      "chinese": "也許",
      "pinyin": "yěxǔ",
      "en": "perhaps; maybe",
      "vi": "có lẽ",
      "sinoVietnamese": "",
      "samples": [
        {
          "type": "Adverb",
          "meaning": "perhaps; probably; maybe",
          "sentence": "我們也許用得上他。",
          "pinyin": "wǒmen yěxǔ yòng dé shàng tā.",
          "en": "He might be useful to us.",
          "vi": ""
        },
        {
          "type": "Adverb",
          "meaning": "perhaps; probably; maybe",
          "sentence": "也許他打算離開她。",
          "pinyin": "yěxǔ tā dǎsuàn líkāi tā.",
          "en": "Maybe he intends to leave her.",
          "vi": ""
        }
      ]
    },
    {
      "id": 73,
      "chinese": "政治界",
      "pinyin": "zhèngzhìjiè",
      "en": "the political world",
      "vi": "giới chính trị",
      "sinoVietnamese": "",
      "samples": [
        {
          "type": "Noun",
          "meaning": "politics; political affairs",
          "sentence": "他對政治很感興趣。",
          "pinyin": "tā duì zhèngzhì hěn gǎn xìngqù.",
          "en": "He is very interested in politics.",
          "vi": "Anh ấy rất quan tâm đến chính trị."
        },
        {
          "type": "Noun",
          "meaning": "politics; political affairs",
          "sentence": "學校有政治活動。",
          "pinyin": "xuéxiào yǒu zhèngzhì huódòng.",
          "en": "There are political activities in the school.",
          "vi": "Trường có các hoạt động chính trị."
        }
      ]
    },
    {
      "id": 74,
      "chinese": "權力",
      "pinyin": "quánlì",
      "en": "power",
      "vi": "quyền lực",
      "sinoVietnamese": "",
      "samples": [
        {
          "type": "Noun",
          "meaning": "power; authority",
          "sentence": "權力鬥爭在政界很常見。",
          "pinyin": "quánlì dòuzhēng zài zhèngjiè hěn chángjiàn.",
          "en": "Power struggles are common in politics.",
          "vi": "Đấu tranh quyền lực trong chính trị rất phổ biến."
        },
        {
          "type": "Noun",
          "meaning": "power; authority",
          "sentence": "他在公司中權力很高。",
          "pinyin": "tā zài gōngsī zhōng quánlì hěn gāo.",
          "en": "He has a lot of power in the company.",
          "vi": "Anh ấy có quyền lực rất cao trong công ty."
        }
      ]
    },
    {
      "id": 75,
      "chinese": "辭掉",
      "pinyin": "cídiào",
      "en": "to quit; to resign from",
      "vi": "từ bỏ; nghỉ hẳn",
      "sinoVietnamese": "",
      "samples": [
        {
          "type": "Verb",
          "meaning": "to dismiss (an employee)",
          "sentence": "老闆決定辭掉他。",
          "pinyin": "lǎobǎn juédìng cí diào tā.",
          "en": "The boss decided to dismiss him.",
          "vi": ""
        },
        {
          "type": "Verb",
          "meaning": "to quit (one's job)",
          "sentence": "你沒必要辭掉工作。",
          "pinyin": "nǐ méi bìyào cídiào gōngzuò。",
          "en": "It is not necessary for you to quit the job.",
          "vi": ""
        }
      ]
    },
    {
      "id": 76,
      "chinese": "提出",
      "pinyin": "tíchū",
      "en": "to propose; to put forward",
      "vi": "đưa ra",
      "sinoVietnamese": "",
      "samples": [
        {
          "type": "Verb",
          "meaning": "to raise; propose; set forth; put forward",
          "sentence": "他提齣了一個好主意。",
          "pinyin": "tā tíchūle yīgè hǎo zhǔyì.",
          "en": "He put forward a good idea.",
          "vi": "Anh ấy đã đưa ra một ý kiến hay."
        },
        {
          "type": "Verb",
          "meaning": "to raise; propose; set forth; put forward",
          "sentence": "老師讓學生提齣問題。",
          "pinyin": "lǎoshī ràng xuéshēng tíchū wèntí.",
          "en": "The teacher asked the students to raise questions.",
          "vi": "Cô giáo yêu cầu học sinh đặt câu hỏi."
        }
      ]
    },
    {
      "id": 77,
      "chinese": "國民年金",
      "pinyin": "guómín niánjīn",
      "en": "national pension",
      "vi": "lương hưu quốc dân",
      "sinoVietnamese": "",
      "samples": [
        {
          "type": "Noun",
          "meaning": "national; member of a nation; people of a nation",
          "sentence": "中國國民很友好。",
          "pinyin": "zhōngguó guómín hěn yǒuhǎo.",
          "en": "Chinese nationals are very friendly.",
          "vi": ""
        },
        {
          "type": "Noun",
          "meaning": "national; member of a nation; people of a nation",
          "sentence": "國民經濟不斷髮/發展。",
          "pinyin": "guómín jīngjì bú duàn fāzhǎn.",
          "en": "The national economy keeps growing.",
          "vi": ""
        }
      ]
    },
    {
      "id": 78,
      "chinese": "中間選民",
      "pinyin": "zhōngjiān xuǎnmín",
      "en": "swing voters",
      "vi": "cử tri trung lập",
      "sinoVietnamese": "",
      "samples": [
        {
          "type": "Noun",
          "meaning": "midst; among",
          "sentence": "我的朋友中間有姓趙的。",
          "pinyin": "wǒ de péngyǒu zhōngjiān yǒu xìng zhào de.",
          "en": "Among my friends, there is someone with the surname Zhao.",
          "vi": ""
        },
        {
          "type": "Noun",
          "meaning": "midst; among",
          "sentence": "你們中間有會唱歌的嗎?",
          "pinyin": "nǐmen zhōngjiān yǒu huì chànggē de ma?",
          "en": "Is there anyone among you who can sing?",
          "vi": ""
        }
      ]
    },
    {
      "id": 79,
      "chinese": "一陣子",
      "pinyin": "yí zhènzi",
      "en": "a period of time",
      "vi": "một thời gian",
      "sinoVietnamese": "",
      "samples": [
        {
          "type": "Noun",
          "meaning": "a spell; a period of time",
          "sentence": "我等了他一陣子。",
          "pinyin": "wǒ děngle tā yī zhènzi.",
          "en": "I waited for him for a while.",
          "vi": "Tôi đã đợi anh ấy một lúc."
        },
        {
          "type": "Noun",
          "meaning": "a spell; a period of time",
          "sentence": "雨下了一陣子就停了。",
          "pinyin": "yǔ xiàle yī zhènzi jiù tíngle.",
          "en": "The rain stopped after a while.",
          "vi": "Mưa rơi một lúc rồi tạnh."
        }
      ]
    },
    {
      "id": 80,
      "chinese": "下一步",
      "pinyin": "xià yí bù",
      "en": "next step",
      "vi": "bước tiếp theo",
      "sinoVietnamese": "",
      "samples": [
        {
          "type": "Noun",
          "meaning": "the next step",
          "sentence": "下一步怎麼做。",
          "pinyin": "xià yībù zěnyāo zuò",
          "en": "What's the next step?",
          "vi": ""
        },
        {
          "type": "Noun",
          "meaning": "the next step",
          "sentence": "這一炮打響了, 下一步就好辦了。",
          "pinyin": "Zhè yī pào dǎxiǎng le, xià yī bù jiù hǎo bàn le.",
          "en": "Success at this stage will make the next step easier.",
          "vi": ""
        }
      ]
    },
    {
      "id": 81,
      "chinese": "盡可能",
      "pinyin": "jǐn kěnéng",
      "en": "as much as possible",
      "vi": "hết khả năng",
      "sinoVietnamese": "",
      "samples": [
        {
          "type": "Adverb",
          "meaning": "as far as possible; to the best of one's ability",
          "sentence": "我會儘可能幫助你。",
          "pinyin": "wǒ huì jǐn kěnéng bāngzhù nǐ.",
          "en": "I'll do my best to help you.",
          "vi": "Tôi sẽ giúp bạn hết sức mình."
        },
        {
          "type": "Adverb",
          "meaning": "as far as possible; to the best of one's ability",
          "sentence": "我會儘可能早點到。",
          "pinyin": "wǒ huì jǐn kěnéng zǎodiǎn dào.",
          "en": "I'll arrive as early as possible.",
          "vi": "Tôi sẽ cố gắng đến sớm nhất có thể."
        }
      ]
    },
    {
      "id": 82,
      "chinese": "出版社",
      "pinyin": "chūbǎnshè",
      "en": "publishing company",
      "vi": "nhà xuất bản",
      "sinoVietnamese": "",
      "samples": [
        {
          "type": "Noun",
          "meaning": "press; publishing house",
          "sentence": "他在齣版社工作。",
          "pinyin": "tā zài chūbǎn shè gōngzuò.",
          "en": "He works at the publishing house.",
          "vi": ""
        },
        {
          "type": "Noun",
          "meaning": "press; publishing house",
          "sentence": "這傢齣版社齣版了很多書。",
          "pinyin": "zhè jiā chūbǎn shè chūbǎnle hěnduō shū.",
          "en": "This publishing house has published many books.",
          "vi": ""
        }
      ]
    },
    {
      "id": 83,
      "chinese": "捐出",
      "pinyin": "juānchū",
      "en": "to donate",
      "vi": "quyên tặng",
      "sinoVietnamese": "",
      "samples": [
        {
          "type": "verb",
          "meaning": "sacrifice; contribute",
          "sentence": "他為了國傢捐軀。",
          "pinyin": "tā wèile guójiā juānqū.",
          "en": "He sacrificed his life for his country.",
          "vi": ""
        },
        {
          "type": "verb",
          "meaning": "sacrifice; contribute",
          "sentence": "英雄無畏地捐齣自己。",
          "pinyin": "yīngxióng wúwèi de juān chū zìjǐ.",
          "en": "Heroes selflessly donated themselves.",
          "vi": ""
        }
      ]
    },
    {
      "id": 84,
      "chinese": "二手書",
      "pinyin": "èrshǒushū",
      "en": "secondhand book",
      "vi": "sách cũ",
      "sinoVietnamese": "",
      "samples": [
        {
          "type": "Noun",
          "meaning": "book",
          "sentence": "她把書放在桌子上。",
          "pinyin": "tā bǎ shū fàng zài zhuōzi shàng.",
          "en": "She put the book on the table.",
          "vi": "Cô ấy đặt sách lên bàn."
        },
        {
          "type": "Noun",
          "meaning": "book",
          "sentence": "我忘了帶教科書。",
          "pinyin": "wǒ wàngle dài jiàokēshū.",
          "en": "I forgot to bring the textbook.",
          "vi": "Tôi quên mang sách giáo khoa."
        }
      ]
    }
  ],
  "verified": false
}
